nn_config.py
qnn_config.py
quicknn.py
quicknn-1.0.9.dist-info/LICENSE.md
quicknn-1.0.9.dist-info/METADATA
quicknn-1.0.9.dist-info/WHEEL
quicknn-1.0.9.dist-info/top_level.txt
quicknn-1.0.9.dist-info/RECORD
