Metadata-Version: 2.1
Name: quicknn
Version: 1.0.9
Summary: An implementation of Feedforward Neural Networks for quick applications.
Home-page: https://gitlab.com/deeplego/quicknn
Author: Lorenzo Palloni
Author-email: palloni.lorenzo@gmail.com
License: UNKNOWN
Platform: UNKNOWN
Classifier: Programming Language :: Python :: 3
Classifier: License :: OSI Approved :: MIT License
Classifier: Operating System :: OS Independent
